nonebot_plugin_localstore/__init__.py
nonebot_plugin_localstore/config.py
nonebot_plugin_localstore/data_source.py
nonebot_plugin_localstore/py.typed
nonebot_plugin_localstore/script.py
nonebot_plugin_localstore/utils.py
nonebot_plugin_localstore-0.7.2.dist-info/LICENSE
nonebot_plugin_localstore-0.7.2.dist-info/METADATA
nonebot_plugin_localstore-0.7.2.dist-info/WHEEL
nonebot_plugin_localstore-0.7.2.dist-info/entry_points.txt
nonebot_plugin_localstore-0.7.2.dist-info/RECORD
