Metadata-Version: 2.1
Name: nonebot-plugin-localstore
Version: 0.7.2
Summary: Local Storage Support for NoneBot2
Home-page: https://github.com/nonebot/plugin-localstore
License: MIT
Keywords: nonebot2,qq,plugin
Author: yanyongyu
Author-email: yyy@nonebot.dev
Requires-Python: >=3.9,<4.0
Classifier: License :: OSI Approved :: MIT License
Classifier: Programming Language :: Python :: 3
Classifier: Programming Language :: Python :: 3.9
Classifier: Programming Language :: Python :: 3.10
Classifier: Programming Language :: Python :: 3.11
Classifier: Programming Language :: Python :: 3.12
Classifier: Programming Language :: Python :: 3.13
Requires-Dist: nonebot2 (>=2.3.0,<3.0.0)
Requires-Dist: pydantic (>=1.10.0,<3.0.0,!=2.5.0,!=2.5.1)
Requires-Dist: typing-extensions (>=4.0.0,<5.0.0)
Project-URL: Documentation, https://github.com/nonebot/plugin-localstore#readme
Project-URL: Repository, https://github.com/nonebot/plugin-localstore
